ensemble/__init__.py
ensemble/ensemble.py
ensemble/graph.py
ensemble/model.py
ensemble/node.py
ensemble/poller.py
ensemble/types.py
ensemble_pkg-0.0.3.dist-info/LICENSE
ensemble_pkg-0.0.3.dist-info/METADATA
ensemble_pkg-0.0.3.dist-info/WHEEL
ensemble_pkg-0.0.3.dist-info/top_level.txt
ensemble_pkg-0.0.3.dist-info/RECORD
