Metadata-Version: 2.1
Name: ensemble-pkg
Version: 0.0.3
Summary: Combine models, easily.
Home-page: https://github.com/sarthfrey/ensemble
Author: sarthfrey
Author-email: sarth.frey@gmail.com
License: UNKNOWN
Platform: UNKNOWN
Classifier: Development Status :: 1 - Planning
Classifier: Intended Audience :: Developers
Classifier: License :: OSI Approved :: MIT License
Classifier: Operating System :: OS Independent
Classifier: Programming Language :: Python :: 3
Classifier: Natural Language :: English
Classifier: Topic :: Scientific/Engineering :: Artificial Intelligence
Classifier: Topic :: Software Development :: Libraries :: Python Modules
Classifier: Topic :: Software Development :: Version Control :: Git
Classifier: Typing :: Typed
Requires-Dist: numpy (>=1.0.0)
